ndms2_client/__init__.py
ndms2_client/client.py
ndms2_client/connection.py
ndms2_client-0.0.3.dist-info/METADATA
ndms2_client-0.0.3.dist-info/RECORD
ndms2_client-0.0.3.dist-info/WHEEL
ndms2_client-0.0.3.dist-info/top_level.txt
