Metadata-Version: 2.1
Name: ndms2-client
Version: 0.0.3
Summary: Keenetic NDMS2 client
Home-page: https://github.com/foxel/python_ndms2_client
Author: Andrey F. Kupreychik
Author-email: foxel@quickfox.ru
License: UNKNOWN
Platform: UNKNOWN
Classifier: Programming Language :: Python :: 3
Classifier: License :: OSI Approved :: MIT License
Classifier: Operating System :: OS Independent
